image_processing/__init__.py
image_processing/processing/__init__.py
image_processing/processing/combination.py
image_processing/processing/transformation.py
image_processing/utils/__init__.py
image_processing/utils/io.py
image_processing/utils/plot.py
deyvidareas_image_processing-0.0.2.dist-info/METADATA
deyvidareas_image_processing-0.0.2.dist-info/WHEEL
deyvidareas_image_processing-0.0.2.dist-info/top_level.txt
deyvidareas_image_processing-0.0.2.dist-info/RECORD
