Metadata-Version: 2.1
Name: deyvidareas-image-processing
Version: 0.0.2
Summary: My image processing program.
Home-page: https://github.com/deyvidareas/image_processing.git
Author: DeyvidArêas
Author-email: deyvidsilva.areas@gmail.com
License: UNKNOWN
Platform: UNKNOWN
Requires-Python: >=3.8
Requires-Dist: matplotlib
Requires-Dist: numpy
Requires-Dist: scikit-image (>=0.36.1)
